./PKG-INFO
./README.md
./README_EN.md
./README_ZH-TW.md
./__init__.py
./pyproject.toml
./server.py
./setup.py
./.github/workflows/pypi-publish.yml
bach_meteostat-1.0.0.dist-info/METADATA
bach_meteostat-1.0.0.dist-info/WHEEL
bach_meteostat-1.0.0.dist-info/entry_points.txt
bach_meteostat-1.0.0.dist-info/RECORD
